ccdefundamentals/__init__.py
ccdefundamentals/block.py
ccdefundamentals/ccdscan.py
ccdefundamentals/cis.py
ccdefundamentals/cns.py
ccdefundamentals/credential.py
ccdefundamentals/enums.py
ccdefundamentals/env.py
ccdefundamentals/mongodb.py
ccdefundamentals/node.py
ccdefundamentals/pool.py
ccdefundamentals/rewards.py
ccdefundamentals/tooter.py
ccdefundamentals/transaction.py
ccdefundamentals/user_v2.py
ccdefundamentals/GRPCClient/__init__.py
ccdefundamentals/GRPCClient/health_pb2.py
ccdefundamentals/GRPCClient/health_pb2.pyi
ccdefundamentals/GRPCClient/health_pb2_grpc.py
ccdefundamentals/GRPCClient/service_pb2.py
ccdefundamentals/GRPCClient/service_pb2.pyi
ccdefundamentals/GRPCClient/service_pb2_grpc.py
ccdefundamentals/GRPCClient/types_pb2.py
ccdefundamentals/GRPCClient/types_pb2.pyi
ccdefundamentals/GRPCClient/types_pb2_grpc.py
ccdefundamentals/GRPCClient/wadze.py
ccdefundamentals/GRPCClient/CCD_Types/__init__.py
ccdefundamentals/GRPCClient/concordium/__init__.py
ccdefundamentals/GRPCClient/concordium/health/__init__.py
ccdefundamentals/GRPCClient/concordium/v2/__init__.py
ccdefundamentals/GRPCClient/queries/_CheckHealth.py
ccdefundamentals/GRPCClient/queries/_GetAccountInfo.py
ccdefundamentals/GRPCClient/queries/_GetAccountList.py
ccdefundamentals/GRPCClient/queries/_GetAnonymityRevokers.py
ccdefundamentals/GRPCClient/queries/_GetBakerEarliestWinTime.py
ccdefundamentals/GRPCClient/queries/_GetBakerList.py
ccdefundamentals/GRPCClient/queries/_GetBlockChainParameters.py
ccdefundamentals/GRPCClient/queries/_GetBlockInfo.py
ccdefundamentals/GRPCClient/queries/_GetBlockPendingUpdates.py
ccdefundamentals/GRPCClient/queries/_GetBlockSpecialEvents.py
ccdefundamentals/GRPCClient/queries/_GetBlockTransactionEvents.py
ccdefundamentals/GRPCClient/queries/_GetBlocksAtHeight.py
ccdefundamentals/GRPCClient/queries/_GetConsensusInfo.py
ccdefundamentals/GRPCClient/queries/_GetElectionInfo.py
ccdefundamentals/GRPCClient/queries/_GetFinalizedBlocks.py
ccdefundamentals-0.1.6.dist-info/LICENSE.md
ccdefundamentals-0.1.6.dist-info/METADATA
ccdefundamentals-0.1.6.dist-info/WHEEL
ccdefundamentals-0.1.6.dist-info/top_level.txt
ccdefundamentals-0.1.6.dist-info/RECORD
