Metadata-Version: 2.1
Name: ccdefundamentals
Version: 0.1.6
Summary: Shared code for CCDExplorer.io and its Notification Bot.
Home-page: https://github.com/ccdexplorer/ccdefundamentals
Author: Sander de Ruiter
Author-email: sdr@ccdexplorer.io
License: Apache-2.0
License-File: LICENSE.md
Requires-Dist: rich
Requires-Dist: python-dateutil
Requires-Dist: base58
Requires-Dist: eth-hash
Requires-Dist: pycryptodome
Requires-Dist: pytest
Requires-Dist: leb128
Requires-Dist: pydantic
Requires-Dist: pymongo
Requires-Dist: motor
Requires-Dist: requests
Requires-Dist: apprise
Requires-Dist: py-graphql-client
Requires-Dist: chardet
